DataFrameProcessor/__init__.py
DataFrameProcessor/categorical_encoder.py
DataFrameProcessor/date_time_handler.py
DataFrameProcessor/feature_engineer.py
DataFrameProcessor/missing_value_handler.py
DataFrameProcessor/outlier_handler.py
DataFrameProcessor/scaler.py
DataFrameProcessor/search.py
DataFrameProcessor/setup.py
DataFrameProcessor/text_cleaner.py
DataFrameProcessor-1.0.1.dist-info/METADATA
DataFrameProcessor-1.0.1.dist-info/WHEEL
DataFrameProcessor-1.0.1.dist-info/top_level.txt
DataFrameProcessor-1.0.1.dist-info/RECORD
