Metadata-Version: 2.1
Name: DataFrameProcessor
Version: 1.0.1
Requires-Python: >=3.6
Requires-Dist: pandas
Requires-Dist: scikit-learn
Requires-Dist: nltk
Requires-Dist: numpy
